{"suspend":"systemctl suspend","editor":"nvim","passwd":"awesomewm","files":"nemo","font":"Iosevka Nerd Font Regular 11","fonticon":"Material Icons 16","exit":"awesome-client command \"awesome.quit()\"","color":"catppuccin","reboot":"systemctl reboot","music":"xst -e ncmpcpp","titlecontrols":true,"panelcontrols":false,"fontalt":"Iosevka Nerd Font Italic 11","editorcmd":"xst -e nvim","browser":"librewolf","sessionlock":false,"batt":"BAT0","terminal":"xst","config":"nemo ~/.config/awesome/","shutdown":"systemctl poweroff","lock":"awesome-client command \"lockscreen()\"","mod":"Mod4"}
